odoo/addons/crm_cooperator/__init__.py
odoo/addons/crm_cooperator/__manifest__.py
odoo/addons/crm_cooperator/models/__init__.py
odoo/addons/crm_cooperator/models/crm_lead.py
odoo/addons/crm_cooperator/models/subscription_request.py
odoo/addons/crm_cooperator/security/ir.model.access.csv
odoo/addons/crm_cooperator/views/crm_lead.xml
odoo12_addon_crm_cooperator-12.0.0.0.1.dist-info/METADATA
odoo12_addon_crm_cooperator-12.0.0.0.1.dist-info/WHEEL
odoo12_addon_crm_cooperator-12.0.0.0.1.dist-info/top_level.txt
odoo12_addon_crm_cooperator-12.0.0.0.1.dist-info/RECORD
